qgis_map/__init__.py
qgis_map/basemaps.py
qgis_map/common.py
qgis_map/qgis_map.py
qgis_map-0.2.0.dist-info/licenses/LICENSE
qgis_map-0.2.0.dist-info/METADATA
qgis_map-0.2.0.dist-info/WHEEL
qgis_map-0.2.0.dist-info/entry_points.txt
qgis_map-0.2.0.dist-info/top_level.txt
qgis_map-0.2.0.dist-info/RECORD
