Metadata-Version: 2.4
Name: qgis-map
Version: 0.2.0
Summary: a Python library that provides a high-level, leafmap-like API for working with PyQGIS
Author-email: Qiusheng Wu <giswqs@gmail.com>
License: MIT License
Project-URL: Homepage, https://github.com/giswqs/qgis-map
Keywords: qgis-map
Classifier: Intended Audience :: Developers
Classifier: License :: OSI Approved :: MIT License
Classifier: Natural Language :: English
Classifier: Programming Language :: Python :: 3.10
Classifier: Programming Language :: Python :: 3.11
Classifier: Programming Language :: Python :: 3.12
Requires-Python: >=3.10
License-File: LICENSE
Requires-Dist: numpy
Provides-Extra: all
Requires-Dist: qgis-map[extra]; extra == "all"
Provides-Extra: extra
Requires-Dist: pandas; extra == "extra"
Dynamic: license-file
